aionuki/__init__.py
aionuki/bridge.py
aionuki/constants.py
aionuki/device.py
aionuki/exceptions.py
aionuki/lock.py
aionuki/opener.py
aionuki/utils.py
aionuki-2.0.1.dist-info/LICENSE
aionuki-2.0.1.dist-info/METADATA
aionuki-2.0.1.dist-info/WHEEL
aionuki-2.0.1.dist-info/top_level.txt
aionuki-2.0.1.dist-info/RECORD
