Metadata-Version: 2.1
Name: aionuki
Version: 2.0.1
Summary: Asynchronous python bindings for nuki.io bridges.
Home-page: https://github.com/rgon/aionuki
Author: Gonzalo Ruiz
License: GPL3
Platform: UNKNOWN
Classifier: Development Status :: 3 - Alpha
Classifier: Intended Audience :: Developers
Classifier: Topic :: Home Automation
Classifier: License :: OSI Approved :: GNU General Public License v3 (GPLv3)
Classifier: Programming Language :: Python :: 3 :: Only
Classifier: Programming Language :: Python :: 3.7
Requires-Dist: aiohttp
